ulumislam/__init__.py
ulumislam-1.0.0.dist-info/LICENSE
ulumislam-1.0.0.dist-info/METADATA
ulumislam-1.0.0.dist-info/WHEEL
ulumislam-1.0.0.dist-info/entry_points.txt
ulumislam-1.0.0.dist-info/top_level.txt
ulumislam-1.0.0.dist-info/RECORD
